dataPreprocess/__init__.py
dataPreprocess/emo_unicode.py
dataPreprocess/preprocess.py
dataPreprocess-0.2.7.dist-info/METADATA
dataPreprocess-0.2.7.dist-info/WHEEL
dataPreprocess-0.2.7.dist-info/entry_points.txt
dataPreprocess-0.2.7.dist-info/top_level.txt
dataPreprocess-0.2.7.dist-info/RECORD
