Metadata-Version: 2.1
Name: dataPreprocess
Version: 0.2.7
Summary: Pre process the textual data for NLP and machine learning applications
Home-page: https://github.com/praveen-AIT/dataPreprocess
Author: Parveen Kumar
Author-email: markrash4@gmail.com
License: MIT
Platform: UNKNOWN
Classifier: License :: OSI Approved :: MIT License
Classifier: Programming Language :: Python :: 3
Classifier: Programming Language :: Python :: 3.7
Requires-Dist: nltk
Requires-Dist: beautifulsoup4
Requires-Dist: spacy
Requires-Dist: unidecode
Requires-Dist: word2number
Requires-Dist: gensim
Requires-Dist: pyspellchecker
Requires-Dist: inflect
